s3_manager/__init__.py
s3_manager/s3_manager.py
modelmaster-0.1.0.dist-info/METADATA
modelmaster-0.1.0.dist-info/WHEEL
modelmaster-0.1.0.dist-info/top_level.txt
modelmaster-0.1.0.dist-info/RECORD
